setup.py
egen111222_test_new_project_12312321321321.egg-info/PKG-INFO
egen111222_test_new_project_12312321321321.egg-info/SOURCES.txt
egen111222_test_new_project_12312321321321.egg-info/dependency_links.txt
egen111222_test_new_project_12312321321321.egg-info/top_level.txt
my_project/__init__.py
my_project/module1.py
my_project/module2.py
my_project/module3.py