Metadata-Version: 2.1
Name: egen111222-test-new-project-12312321321321
Version: 1.0
Summary: New Test Projects
Author: egen111222
Author-email: egen13@ukr.net
